{
  "domain": "nonfiction",
  "sample_size": 480,
  "timestamp": "2025-11-18T19:07:29.654553",
  "domain_info": {
    "name": "nonfiction",
    "estimated_pi": 0.75,
    "sample_size": 480,
    "total_available": 480,
    "outcome_type": "continuous",
    "used_transformers": true,
    "fast_mode": false
  },
  "n_patterns": 8,
  "patterns": [
    {
      "id": "pattern_0",
      "size": 60,
      "size_pct": 0.125,
      "centroid_latent": [
        -12.026875410835341,
        52.69725200320227,
        16.333128008587423,
        3.16240012107415,
        4.137814407817158,
        3.7079859957066974,
        -3.5847887350865477,
        -0.8416992442850426,
        -1.606563054824709,
        -1.3288054682127306,
        0.20363616358231323,
        0.4666857950618082,
        0.24399835054836425,
        -0.41749432248252016,
        -0.004851846822603397,
        -1.6424774099438209,
        0.7912318194339217,
        0.012258475274413703,
        -0.15789351554983108,
        0.5572506381720235,
        -0.18888526509186232,
        -0.13255855164771976,
        0.05931574803525825,
        -0.017001287027608638,
        -0.04363816968762941,
        0.09917742020345158,
        -0.04677343854411738,
        0.17878588944795734,
        -0.029518409043536403,
        0.0876682683969569,
        0.030619917790466078,
        -0.05118411612237,
        0.028102944120907598,
        0.1286950715552427,
        -0.19128239876711603,
        0.05808303997181468,
        0.03029786963381975,
        -0.1602040412658539,
        0.1143536145788915,
        -0.02250957641283636,
        -0.06555038166498861,
        0.03784682798431725,
        -0.029197490424563623,
        -0.15405830726735148,
        0.02139450551005367,
        0.06379719281282649,
        -0.135435692987456,
        0.06252516090452304,
        0.06898185938201035,
        0.0040252085642529375
      ],
      "variance": 68.66005280054085,
      "std": 8.286136180424556,
      "density": 0.08156887901560474,
      "separation": 1.0,
      "coherence": 0.05655174087027075,
      "example_narratives": [
        "Invisible Child by Andrea Elliott is a significant work of nonfiction. The book explores important themes and provides insightful analysis of its subject matter. Through compelling narrative and thorough research, it offers readers a deeper understanding of complex topics. Excerpt from Invisible Child: [Full text excerpt would be included here from the actual book or public domain sources]",
        "Becoming by Michelle Obama is a significant work of nonfiction. The book explores important themes and provides insightful analysis of its subject matter. Through compelling narrative and thorough research, it offers readers a deeper understanding of complex topics. Excerpt from Becoming: [Full text excerpt would be included here from the actual book or public domain sources]",
        "Sapiens by Yuval Noah Harari is a significant work of nonfiction. The book explores important themes and provides insightful analysis of its subject matter. Through compelling narrative and thorough research, it offers readers a deeper understanding of complex topics. Excerpt from Sapiens: [Full text excerpt would be included here from the actual book or public domain sources]",
        "Quiet by Susan Cain is a significant work of nonfiction. The book explores important themes and provides insightful analysis of its subject matter. Through compelling narrative and thorough research, it offers readers a deeper understanding of complex topics. Excerpt from Quiet: [Full text excerpt would be included here from the actual book or public domain sources]",
        "Outliers by Malcolm Gladwell is a significant work of nonfiction. The book explores important themes and provides insightful analysis of its subject matter. Through compelling narrative and thorough research, it offers readers a deeper understanding of complex topics. Excerpt from Outliers: [Full text excerpt would be included here from the actual book or public domain sources]"
      ],
      "latent_signature": {
        "prominent_dimensions": [
          1,
          2,
          0,
          4,
          5,
          6,
          3,
          15,
          8,
          9
        ],
        "dimension_values": [
          52.69725200320227,
          16.333128008587423,
          -12.026875410835341,
          4.137814407817158,
          3.7079859957066974,
          -3.5847887350865477,
          3.16240012107415,
          -1.6424774099438209,
          -1.606563054824709,
          -1.3288054682127306
        ],
        "dimension_prominence": [
          0.49589685382845006,
          0.15369960452859388,
          0.1131764836097634,
          0.038938067329163,
          0.034893253811397344,
          0.033733930855845445,
          0.029759128056470265,
          0.015456202156916024,
          0.015118237366840006,
          0.012504455659219023
        ],
        "note": "These dimensions predict patterns. What they MEAN remains elusive."
      }
    },
    {
      "id": "pattern_1",
      "size": 115,
      "size_pct": 0.23958333333333334,
      "centroid_latent": [
        -17.902786680080084,
        -34.741498731127116,
        9.162011496970878,
        -6.332600584143235,
        4.357883624433258,
        0.49162137325682304,
        0.47618176557621184,
        -0.7105693775040083,
        -0.9740432438038987,
        -0.07652104960461997,
        -2.2287058180537875,
        -0.6435644201836772,
        0.654674280728664,
        -0.02167094356938469,
        0.8201337807928886,
        -0.3429502366162806,
        -0.06297401681596332,
        0.28438177322848446,
        0.1446743874956822,
        -0.2601026195661475,
        0.14246967698464294,
        -0.06597697558828272,
        -0.06503676746635564,
        0.04377224044814878,
        0.07100005433425079,
        -0.02033388512473846,
        0.05068771365189144,
        -0.127676326998185,
        -0.06454350345931913,
        -0.11908616048615796,
        -0.10263892220021528,
        0.08356805619829762,
        -0.021706300597131436,
        0.10229460622557986,
        0.0954947501992411,
        -0.042410250996069425,
        -0.040351516348250474,
        0.10713626072273127,
        -0.10412133778463334,
        -0.04362428484416678,
        -0.02776123826093215,
        -0.006987743391245658,
        -0.007973001965010827,
        -0.022032847707592253,
        -0.025419531495040337,
        -0.002534979842671212,
        0.03538131745929673,
        0.02776966948017928,
        -0.03319116554253882,
        -0.020705452450548858
      ],
      "variance": 34.73289394519763,
      "std": 5.893461966043187,
      "density": 0.09886228580070346,
      "separation": 1.0,
      "coherence": 0.07163358706247057,
      "example_narratives": [
        "The Sixth Extinction by Elizabeth Kolbert is a significant work of nonfiction. The book explores important themes and provides insightful analysis of its subject matter. Through compelling narrative and thorough research, it offers readers a deeper understanding of complex topics. Excerpt from The Sixth Extinction: [Full text excerpt would be included here from the actual book or public domain sources]",
        "The Swerve by Stephen Greenblatt is a significant work of nonfiction. The book explores important themes and provides insightful analysis of its subject matter. Through compelling narrative and thorough research, it offers readers a deeper understanding of complex topics. Excerpt from The Swerve: [Full text excerpt would be included here from the actual book or public domain sources]",
        "The Dead Hand by David E. Hoffman is a significant work of nonfiction. The book explores important themes and provides insightful analysis of its subject matter. Through compelling narrative and thorough research, it offers readers a deeper understanding of complex topics. Excerpt from The Dead Hand: [Full text excerpt would be included here from the actual book or public domain sources]",
        "The Years of Extermination by Saul Friedl\u00e4nder is a significant work of nonfiction. The book explores important themes and provides insightful analysis of its subject matter. Through compelling narrative and thorough research, it offers readers a deeper understanding of complex topics. Excerpt from The Years of Extermination: [Full text excerpt would be included here from the actual book or public domain sources]",
        "The Looming Tower by Lawrence Wright is a significant work of nonfiction. The book explores important themes and provides insightful analysis of its subject matter. Through compelling narrative and thorough research, it offers readers a deeper understanding of complex topics. Excerpt from The Looming Tower: [Full text excerpt would be included here from the actual book or public domain sources]"
      ],
      "latent_signature": {
        "prominent_dimensions": [
          1,
          0,
          2,
          3,
          4,
          10,
          8,
          14,
          7,
          12
        ],
        "dimension_values": [
          -34.741498731127116,
          -17.902786680080084,
          9.162011496970878,
          -6.332600584143235,
          4.357883624433258,
          -2.2287058180537875,
          -0.9740432438038987,
          0.8201337807928886,
          -0.7105693775040083,
          0.654674280728664
        ],
        "dimension_prominence": [
          0.4215524120229628,
          0.2172319324888113,
          0.11117160130083101,
          0.07683960531707887,
          0.05287844279294888,
          0.02704305650603416,
          0.01181901454563077,
          0.009951481257341185,
          0.008622029732070567,
          0.00794380012982281
        ],
        "note": "These dimensions predict patterns. What they MEAN remains elusive."
      }
    },
    {
      "id": "pattern_2",
      "size": 67,
      "size_pct": 0.13958333333333334,
      "centroid_latent": [
        97.8935186000735,
        -4.046014771911626,
        -1.53108742423669,
        -4.58306802058078,
        -2.251563759672229,
        -0.736835657139142,
        -0.7983330964899138,
        0.9397417717522867,
        0.3032699527413369,
        0.3698936168658246,
        0.07645442232801375,
        0.0077146105554986785,
        -0.00537857772894682,
        0.07578453306568686,
        0.22890231916951456,
        -0.21326844439169335,
        0.06308063462824323,
        -0.05962052504595989,
        -0.14771086330183927,
        0.06348292789834607,
        -0.02277080265566165,
        -0.004704388713850443,
        -0.01725114565694273,
        0.040527611543054495,
        0.0023834978413848702,
        0.0380895649278907,
        -0.04789940702517864,
        0.051347426533229476,
        0.006395705438311971,
        0.04156272149238094,
        0.01790130354994605,
        -0.01523109457306835,
        -0.003828860457487946,
        0.030066453175219363,
        0.004436995511679155,
        -0.07164612816003774,
        0.05449169825343132,
        -0.0008001193552451806,
        0.08192342507448376,
        -0.08343659870429254,
        -0.00531280011191921,
        0.006674510356482077,
        0.023395460980480492,
        -0.03299404818583018,
        0.01842386954715502,
        0.0012947665619971829,
        -0.01526332783038797,
        0.013672378275092137,
        0.006513811813803814,
        -0.014911091788995079
      ],
      "variance": 195.7971709798353,
      "std": 13.992754231381157,
      "density": 0.07739312534345368,
      "separation": 1.0,
      "coherence": 0.052701193983144504,
      "example_narratives": [
        "Devil in the Grove by Gilbert King is a significant work of nonfiction. The book explores important themes and provides insightful analysis of its subject matter. Through compelling narrative and thorough research, it offers readers a deeper understanding of complex topics. Excerpt from Devil in the Grove: [Full text excerpt would be included here from the actual book or public domain sources]",
        "In Defense of Food by Michael Pollan is a significant work of nonfiction. The book explores important themes and provides insightful analysis of its subject matter. Through compelling narrative and thorough research, it offers readers a deeper understanding of complex topics. Excerpt from In Defense of Food: [Full text excerpt would be included here from the actual book or public domain sources]",
        "In Cold Blood by Truman Capote is a significant work of nonfiction. The book explores important themes and provides insightful analysis of its subject matter. Through compelling narrative and thorough research, it offers readers a deeper understanding of complex topics. Excerpt from In Cold Blood: [Full text excerpt would be included here from the actual book or public domain sources]",
        "A People's History of the United States by Howard Zinn is a significant work of nonfiction. The book explores important themes and provides insightful analysis of its subject matter. Through compelling narrative and thorough research, it offers readers a deeper understanding of complex topics. Excerpt from A People's History of the United States: [Full text excerpt would be included here from the actual book or public domain sources]",
        "A Brief History of Time by Stephen Hawking is a significant work of nonfiction. The book explores important themes and provides insightful analysis of its subject matter. Through compelling narrative and thorough research, it offers readers a deeper understanding of complex topics. Excerpt from A Brief History of Time: [Full text excerpt would be included here from the actual book or public domain sources]"
      ],
      "latent_signature": {
        "prominent_dimensions": [
          0,
          3,
          1,
          4,
          2,
          7,
          6,
          5,
          9,
          8
        ],
        "dimension_values": [
          97.8935186000735,
          -4.58306802058078,
          -4.046014771911626,
          -2.251563759672229,
          -1.53108742423669,
          0.9397417717522867,
          -0.7983330964899138,
          -0.736835657139142,
          0.3698936168658246,
          0.3032699527413369
        ],
        "dimension_prominence": [
          0.8499923972128688,
          0.03979398257526898,
          0.035130842616717006,
          0.01954993655279626,
          0.013294165831203901,
          0.008159614372388031,
          0.006931787437654987,
          0.006397815866873422,
          0.003211721946556783,
          0.0026332402575735877
        ],
        "note": "These dimensions predict patterns. What they MEAN remains elusive."
      }
    },
    {
      "id": "pattern_3",
      "size": 42,
      "size_pct": 0.0875,
      "centroid_latent": [
        -29.340681608430735,
        31.39340675325955,
        -32.66046691127661,
        -23.377147776820145,
        6.371610522445999,
        -4.4705207995309815,
        -1.5092209396195848,
        1.5436747502965358,
        0.8729061717036737,
        -0.36222587128234107,
        1.411484463959215,
        -0.25927654260535826,
        -0.37586103534984994,
        0.39381039543129887,
        0.26729178729956193,
        0.011268849746889591,
        0.14921269714840688,
        -0.04526884459277799,
        0.03920729589752968,
        0.04966044993326343,
        0.0017952435790903015,
        -0.03063174703097272,
        -0.003967949251012224,
        -6.693246868968597e-05,
        -0.0028204570015028267,
        -0.13581298631494065,
        0.04172073714107838,
        -0.09324064959992881,
        0.08436629286160964,
        -0.08335570603438021,
        -0.019521810862596158,
        -0.01648662548224952,
        -0.05455402226856852,
        -0.05802062329099036,
        0.01621320685546132,
        -0.0044600592749358264,
        -0.05499139526666121,
        -0.004218468767191667,
        0.050126962540169344,
        -0.04257117872425174,
        -0.05126932035466004,
        -0.020557941702405966,
        0.02124132572009532,
        0.01821925377010141,
        -0.05197612313486829,
        -0.01691993819043816,
        0.032631884992401154,
        -0.005478091784171927,
        -0.032753821677075155,
        0.01610771975062921
      ],
      "variance": 71.84142682384146,
      "std": 8.475932209724277,
      "density": 0.11889605895911733,
      "separation": 1.0,
      "coherence": 0.08309355602142174,
      "example_narratives": [
        "Freakonomics by Steven Levitt and Stephen Dubner is a significant work of nonfiction. The book explores important themes and provides insightful analysis of its subject matter. Through compelling narrative and thorough research, it offers readers a deeper understanding of complex topics. Excerpt from Freakonomics: [Full text excerpt would be included here from the actual book or public domain sources]",
        "Predictably Irrational by Dan Ariely is a significant work of nonfiction. The book explores important themes and provides insightful analysis of its subject matter. Through compelling narrative and thorough research, it offers readers a deeper understanding of complex topics. Excerpt from Predictably Irrational: [Full text excerpt would be included here from the actual book or public domain sources]",
        "Understanding Society by Nicole Young is a significant work of nonfiction. The book explores important themes and provides insightful analysis of its subject matter. Through compelling narrative and thorough research, it offers readers a deeper understanding of complex topics. Excerpt from Understanding Society: [Full text excerpt would be included here from the actual book or public domain sources]",
        "Understanding Politics by Sarah Johnson is a significant work of nonfiction. The book explores important themes and provides insightful analysis of its subject matter. Through compelling narrative and thorough research, it offers readers a deeper understanding of complex topics. Excerpt from Understanding Politics: [Full text excerpt would be included here from the actual book or public domain sources]",
        "Understanding Psychology by Jennifer Brown is a significant work of nonfiction. The book explores important themes and provides insightful analysis of its subject matter. Through compelling narrative and thorough research, it offers readers a deeper understanding of complex topics. Excerpt from Understanding Psychology: [Full text excerpt would be included here from the actual book or public domain sources]"
      ],
      "latent_signature": {
        "prominent_dimensions": [
          2,
          1,
          0,
          3,
          4,
          5,
          7,
          6,
          10,
          8
        ],
        "dimension_values": [
          -32.66046691127661,
          31.39340675325955,
          -29.340681608430735,
          -23.377147776820145,
          6.371610522445999,
          -4.4705207995309815,
          1.5436747502965358,
          -1.5092209396195848,
          1.411484463959215,
          0.8729061717036737
        ],
        "dimension_prominence": [
          0.24020294288180477,
          0.23088428924495494,
          0.21578742544154375,
          0.17192833487130188,
          0.04686030982183471,
          0.03287865587405001,
          0.011353028690031967,
          0.011099636515921964,
          0.010380829000270344,
          0.006419829571711313
        ],
        "note": "These dimensions predict patterns. What they MEAN remains elusive."
      }
    },
    {
      "id": "pattern_4",
      "size": 42,
      "size_pct": 0.0875,
      "centroid_latent": [
        -19.890447729603565,
        15.964632665408875,
        -11.094443766220703,
        14.443167548498096,
        -10.498939193724054,
        0.9787671627212058,
        -0.12828403112253672,
        0.05607652628269792,
        1.3941875170495146,
        4.607049670120899,
        -2.186867050568761,
        0.34241613183439373,
        -0.4007116105154535,
        1.8429024938585097,
        1.452254016061986,
        0.7338424034270633,
        -0.6439553785048973,
        -0.05488811135057608,
        -0.0369483871079802,
        -0.3655465444395669,
        0.5716363375863139,
        -0.029904674738585005,
        -0.2624338004592607,
        0.08960990876382192,
        0.2800054817721769,
        0.3008615793967383,
        -0.10086373772373677,
        -0.0839251484608923,
        -0.318139099504046,
        0.1358277053949942,
        0.13731531762782492,
        0.1626751110668017,
        -0.26016986588314894,
        0.4246594778217876,
        0.21376943181021718,
        0.010994060588184888,
        0.3830994844090406,
        0.16366657538095927,
        -0.1301316414060295,
        -0.2584221945479278,
        -0.1113378885282635,
        -0.054957222012559356,
        -0.015464984329833323,
        -0.0748884600254359,
        0.012251578040434006,
        0.35706302733357703,
        -0.049405831333088776,
        0.03707960652752018,
        -0.03372985668131403,
        0.0640660441683129
      ],
      "variance": 35.69420214060568,
      "std": 5.974462498049986,
      "density": 0.0387603922978295,
      "separation": 0.9994016254721926,
      "coherence": 0.028104421308623763,
      "example_narratives": [
        "Behind the Beautiful Forevers by Katherine Boo is a significant work of nonfiction. The book explores important themes and provides insightful analysis of its subject matter. Through compelling narrative and thorough research, it offers readers a deeper understanding of complex topics. Excerpt from Behind the Beautiful Forevers: [Full text excerpt would be included here from the actual book or public domain sources]",
        "Politics: A New Perspective by Tyler Russell is a significant work of nonfiction. The book explores important themes and provides insightful analysis of its subject matter. Through compelling narrative and thorough research, it offers readers a deeper understanding of complex topics. Excerpt from Politics: A New Perspective: [Full text excerpt would be included here from the actual book or public domain sources]",
        "Politics: An Insider's View by Amanda Lee is a significant work of nonfiction. The book explores important themes and provides insightful analysis of its subject matter. Through compelling narrative and thorough research, it offers readers a deeper understanding of complex topics. Excerpt from Politics: An Insider's View: [Full text excerpt would be included here from the actual book or public domain sources]",
        "Society: Breaking Down the Myths by Andrew Jackson is a significant work of nonfiction. The book explores important themes and provides insightful analysis of its subject matter. Through compelling narrative and thorough research, it offers readers a deeper understanding of complex topics. Excerpt from Society: Breaking Down the Myths: [Full text excerpt would be included here from the actual book or public domain sources]",
        "Science: The Complete Guide by Christopher Davis is a significant work of nonfiction. The book explores important themes and provides insightful analysis of its subject matter. Through compelling narrative and thorough research, it offers readers a deeper understanding of complex topics. Excerpt from Science: The Complete Guide: [Full text excerpt would be included here from the actual book or public domain sources]"
      ],
      "latent_signature": {
        "prominent_dimensions": [
          0,
          1,
          3,
          2,
          4,
          9,
          10,
          13,
          14,
          8
        ],
        "dimension_values": [
          -19.890447729603565,
          15.964632665408875,
          14.443167548498096,
          -11.094443766220703,
          -10.498939193724054,
          4.607049670120899,
          -2.186867050568761,
          1.8429024938585097,
          1.452254016061986,
          1.3941875170495146
        ],
        "dimension_prominence": [
          0.21562703743188735,
          0.17306832365603372,
          0.15657452622244675,
          0.12027190507654405,
          0.11381619887574881,
          0.04994379639786635,
          0.023707242279404926,
          0.019978414283511332,
          0.01574349835353092,
          0.015114014928808116
        ],
        "note": "These dimensions predict patterns. What they MEAN remains elusive."
      }
    },
    {
      "id": "pattern_5",
      "size": 52,
      "size_pct": 0.10833333333333334,
      "centroid_latent": [
        -25.531005700012614,
        7.53756597033402,
        14.992492755735508,
        -3.9651224180759503,
        -13.395662876574658,
        -4.142424566771089,
        4.40072916327388,
        3.281346024647931,
        1.3282218896240292,
        1.2374729581851809,
        1.9565572632277894,
        -0.9381957085127632,
        -0.10080607588267394,
        -1.5277322662743715,
        -0.6764605354386711,
        1.1993636758154542,
        -0.345231862635618,
        -0.4948296994704693,
        -0.25640625052190685,
        -0.05316672677909188,
        -0.27934042272927206,
        0.06973810198099933,
        -0.02053811753555327,
        0.020872063316989868,
        -0.2589710052736628,
        0.0012975838285412453,
        -0.1980567075732189,
        -0.0002821514522042556,
        0.12765983562445493,
        0.06087123116629045,
        -0.09532330770619428,
        -0.03661528149334702,
        0.2740957185535415,
        -0.2499949780612254,
        -0.07485066644900337,
        -0.07896226702883052,
        -0.1827143785092389,
        -0.14049058314138313,
        0.2458841177659459,
        0.07831677005739243,
        -0.021455642416367684,
        0.0939932161023447,
        0.07416068531554365,
        0.07654989638901669,
        0.02522007503430445,
        -0.14405517740221868,
        0.030079735833098125,
        -0.098477831564664,
        0.0529300763664936,
        -0.005138831680785884
      ],
      "variance": 33.2480378580612,
      "std": 5.7661111555415925,
      "density": 0.059211581386536566,
      "separation": 1.0,
      "coherence": 0.040511021351666995,
      "example_narratives": [
        "Locking Up Our Own by James Forman Jr. is a significant work of nonfiction. The book explores important themes and provides insightful analysis of its subject matter. Through compelling narrative and thorough research, it offers readers a deeper understanding of complex topics. Excerpt from Locking Up Our Own: [Full text excerpt would be included here from the actual book or public domain sources]",
        "Evicted by Matthew Desmond is a significant work of nonfiction. The book explores important themes and provides insightful analysis of its subject matter. Through compelling narrative and thorough research, it offers readers a deeper understanding of complex topics. Excerpt from Evicted: [Full text excerpt would be included here from the actual book or public domain sources]",
        "Black Flags by Joby Warrick is a significant work of nonfiction. The book explores important themes and provides insightful analysis of its subject matter. Through compelling narrative and thorough research, it offers readers a deeper understanding of complex topics. Excerpt from Black Flags: [Full text excerpt would be included here from the actual book or public domain sources]",
        "Toms River by Dan Fagin is a significant work of nonfiction. The book explores important themes and provides insightful analysis of its subject matter. Through compelling narrative and thorough research, it offers readers a deeper understanding of complex topics. Excerpt from Toms River: [Full text excerpt would be included here from the actual book or public domain sources]",
        "Stamped from the Beginning by Ibram X. Kendi is a significant work of nonfiction. The book explores important themes and provides insightful analysis of its subject matter. Through compelling narrative and thorough research, it offers readers a deeper understanding of complex topics. Excerpt from Stamped from the Beginning: [Full text excerpt would be included here from the actual book or public domain sources]"
      ],
      "latent_signature": {
        "prominent_dimensions": [
          0,
          2,
          4,
          1,
          6,
          5,
          3,
          7,
          10,
          13
        ],
        "dimension_values": [
          -25.531005700012614,
          14.992492755735508,
          -13.395662876574658,
          7.53756597033402,
          4.40072916327388,
          -4.142424566771089,
          -3.9651224180759503,
          3.281346024647931,
          1.9565572632277894,
          -1.5277322662743715
        ],
        "dimension_prominence": [
          0.282179995690977,
          0.16570367775243414,
          0.14805480587816208,
          0.0833085213336605,
          0.04863881003830439,
          0.04578391310300344,
          0.04382429113814013,
          0.03626689124491873,
          0.021624738429575244,
          0.016885174418101973
        ],
        "note": "These dimensions predict patterns. What they MEAN remains elusive."
      }
    },
    {
      "id": "pattern_6",
      "size": 65,
      "size_pct": 0.13541666666666666,
      "centroid_latent": [
        -14.602058271528035,
        -39.868966833232484,
        -12.10191218945503,
        12.896891767403867,
        0.5671580351494219,
        1.7650826163987743,
        -2.662779760558893,
        -0.5874828567240559,
        0.39308206901452375,
        -1.9907868586272837,
        3.0538324972661632,
        1.5043542400875065,
        -0.6853075331914077,
        0.12587792109138993,
        -1.709684397112434,
        0.013678184219771811,
        0.388487621788648,
        -0.21067227992801094,
        -0.12448301558755838,
        0.5481328927385517,
        -0.2853835346206117,
        0.12077808131450508,
        0.19670490127325704,
        -0.10433257729343524,
        -0.07612781190468475,
        0.0449345247509644,
        -0.0035642923548392944,
        0.2856380187195707,
        0.12730866991966455,
        0.16019718399099106,
        0.17797416562320753,
        -0.16376307723067798,
        0.014695793910178608,
        -0.18124972872009237,
        -0.18717147541409768,
        0.11275776195845276,
        0.05801708377631268,
        -0.14331168991491838,
        0.13355754313047807,
        0.07013908269033661,
        0.0824592814403949,
        0.004737800116910263,
        -0.0074542865143863634,
        0.031919855786817435,
        0.04861021873033961,
        -0.008427937260032383,
        -0.08145461738950817,
        -0.02043106813505018,
        0.027409967391698462,
        0.021762978374774557
      ],
      "variance": 46.02923783059866,
      "std": 6.784485082200319,
      "density": 0.06750454113882932,
      "separation": 1.0,
      "coherence": 0.04877173912052012,
      "example_narratives": [
        "The Dead Are Arising by Les Payne and Tamara Payne is a significant work of nonfiction. The book explores important themes and provides insightful analysis of its subject matter. Through compelling narrative and thorough research, it offers readers a deeper understanding of complex topics. Excerpt from The Dead Are Arising: [Full text excerpt would be included here from the actual book or public domain sources]",
        "The Emperor of All Maladies by Siddhartha Mukherjee is a significant work of nonfiction. The book explores important themes and provides insightful analysis of its subject matter. Through compelling narrative and thorough research, it offers readers a deeper understanding of complex topics. Excerpt from The Emperor of All Maladies: [Full text excerpt would be included here from the actual book or public domain sources]",
        "The Immortal Life of Henrietta Lacks by Rebecca Skloot is a significant work of nonfiction. The book explores important themes and provides insightful analysis of its subject matter. Through compelling narrative and thorough research, it offers readers a deeper understanding of complex topics. Excerpt from The Immortal Life of Henrietta Lacks: [Full text excerpt would be included here from the actual book or public domain sources]",
        "The Warmth of Other Suns by Isabel Wilkerson is a significant work of nonfiction. The book explores important themes and provides insightful analysis of its subject matter. Through compelling narrative and thorough research, it offers readers a deeper understanding of complex topics. Excerpt from The Warmth of Other Suns: [Full text excerpt would be included here from the actual book or public domain sources]",
        "The Autobiography of Malcolm X by Malcolm X and Alex Haley is a significant work of nonfiction. The book explores important themes and provides insightful analysis of its subject matter. Through compelling narrative and thorough research, it offers readers a deeper understanding of complex topics. Excerpt from The Autobiography of Malcolm X: [Full text excerpt would be included here from the actual book or public domain sources]"
      ],
      "latent_signature": {
        "prominent_dimensions": [
          1,
          0,
          3,
          2,
          10,
          6,
          9,
          5,
          14,
          11
        ],
        "dimension_values": [
          -39.868966833232484,
          -14.602058271528035,
          12.896891767403867,
          -12.10191218945503,
          3.0538324972661632,
          -2.662779760558893,
          -1.9907868586272837,
          1.7650826163987743,
          -1.709684397112434,
          1.5043542400875065
        ],
        "dimension_prominence": [
          0.4036015522943034,
          0.14781956627399173,
          0.13055782355405965,
          0.12251008574724559,
          0.03091455922344205,
          0.026955853891945172,
          0.020153134887842965,
          0.017868285548659574,
          0.017307478257318626,
          0.015228879871392638
        ],
        "note": "These dimensions predict patterns. What they MEAN remains elusive."
      }
    },
    {
      "id": "pattern_7",
      "size": 37,
      "size_pct": 0.07708333333333334,
      "centroid_latent": [
        15.29785845680599,
        35.54086437092516,
        -2.332843993833008,
        15.910437506463774,
        6.337467354325231,
        0.4778846355019738,
        6.130613925567788,
        -3.5237412661701635,
        -0.04719292380448746,
        -1.3374235432105526,
        -0.7760396866831054,
        -0.18910350812020746,
        -0.19362491565339285,
        -0.00588308731934172,
        -0.9534113365472807,
        1.5601686981554177,
        -0.8372633971494363,
        0.38342155291201757,
        0.650333272523759,
        -0.7398201479900525,
        0.1477365446897848,
        0.18707114760027713,
        0.1228958689851091,
        -0.12955716692083705,
        0.028827529327373366,
        -0.4347164500098144,
        0.3567895495867578,
        -0.2863645719598788,
        0.09919400156214792,
        -0.2738333767866516,
        -0.07545790273447528,
        0.024050867676499554,
        -0.024951867419089332,
        -0.32751073071080217,
        0.17829401857129315,
        0.07283357718932132,
        -0.23997011048432718,
        0.1964629778292408,
        -0.4995446060658162,
        0.431562938232762,
        0.2720774538517108,
        -0.10644266896872065,
        -0.06792390771908889,
        0.27871888041126486,
        -0.06479731604385618,
        -0.2667671038840693,
        0.2571579094424336,
        -0.07403967400008116,
        -0.06756892641944041,
        -0.037189588209039566
      ],
      "variance": 70.15315053652427,
      "std": 8.37574775984355,
      "density": 0.025975751797682183,
      "separation": 1.0,
      "coherence": 0.01832884133167681,
      "example_narratives": [
        "Amity and Prosperity by Eliza Griswold is a significant work of nonfiction. The book explores important themes and provides insightful analysis of its subject matter. Through compelling narrative and thorough research, it offers readers a deeper understanding of complex topics. Excerpt from Amity and Prosperity: [Full text excerpt would be included here from the actual book or public domain sources]",
        "Slavery by Another Name by Douglas A. Blackmon is a significant work of nonfiction. The book explores important themes and provides insightful analysis of its subject matter. Through compelling narrative and thorough research, it offers readers a deeper understanding of complex topics. Excerpt from Slavery by Another Name: [Full text excerpt would be included here from the actual book or public domain sources]",
        "All That She Carried by Tiya Miles is a significant work of nonfiction. The book explores important themes and provides insightful analysis of its subject matter. Through compelling narrative and thorough research, it offers readers a deeper understanding of complex topics. Excerpt from All That She Carried: [Full text excerpt would be included here from the actual book or public domain sources]",
        "Between the World and Me by Ta-Nehisi Coates is a significant work of nonfiction. The book explores important themes and provides insightful analysis of its subject matter. Through compelling narrative and thorough research, it offers readers a deeper understanding of complex topics. Excerpt from Between the World and Me: [Full text excerpt would be included here from the actual book or public domain sources]",
        "Age of Ambition by Evan Osnos is a significant work of nonfiction. The book explores important themes and provides insightful analysis of its subject matter. Through compelling narrative and thorough research, it offers readers a deeper understanding of complex topics. Excerpt from Age of Ambition: [Full text excerpt would be included here from the actual book or public domain sources]"
      ],
      "latent_signature": {
        "prominent_dimensions": [
          1,
          3,
          0,
          4,
          6,
          7,
          2,
          15,
          9,
          14
        ],
        "dimension_values": [
          35.54086437092516,
          15.910437506463774,
          15.29785845680599,
          6.337467354325231,
          6.130613925567788,
          -3.5237412661701635,
          -2.332843993833008,
          1.5601686981554177,
          -1.3374235432105526,
          -0.9534113365472807
        ],
        "dimension_prominence": [
          0.35952263674744034,
          0.1609460699782166,
          0.1547493710783053,
          0.06410825999470539,
          0.06201578161964473,
          0.03564529939417124,
          0.023598475687873093,
          0.015782282565713974,
          0.013529047399773342,
          0.009644474429293597
        ],
        "note": "These dimensions predict patterns. What they MEAN remains elusive."
      }
    }
  ],
  "significant_correlations": [
    {
      "pattern_id": "pattern_2",
      "correlation_type": "cluster_membership",
      "effect_size": 0.3355545925289881,
      "p_value": 0.010779944887902536,
      "significant": true,
      "cluster_mean": 0.19253731343283584,
      "other_mean": 0.137046004842615,
      "test": "t-test",
      "n_in_cluster": 67,
      "p_value_bonferroni": 0.18325906309434312,
      "p_value_fdr": 0.00894856371210251,
      "significant_bonferroni": false,
      "significant_fdr": true
    },
    {
      "pattern_id": "latent_dim_17",
      "correlation_type": "latent_dimension",
      "effect_size": 0.15396605673860064,
      "p_value": 0.0007127297209699453,
      "significant": true,
      "interpretation": "UNKNOWN - dimension eludes interpretation",
      "note": "Correlation exists. Mechanism remains mysterious.",
      "p_value_bonferroni": 0.01211640525648907,
      "p_value_fdr": 0.01211640525648907,
      "significant_bonferroni": true,
      "significant_fdr": true
    },
    {
      "pattern_id": "latent_dim_6",
      "correlation_type": "latent_dimension",
      "effect_size": 0.14908191058699277,
      "p_value": 0.0010527722014238247,
      "significant": true,
      "interpretation": "UNKNOWN - dimension eludes interpretation",
      "note": "Correlation exists. Mechanism remains mysterious.",
      "p_value_bonferroni": 0.01789712742420502,
      "p_value_fdr": 0.00894856371210251,
      "significant_bonferroni": true,
      "significant_fdr": true
    },
    {
      "pattern_id": "latent_dim_0",
      "correlation_type": "latent_dimension",
      "effect_size": 0.13462974326132812,
      "p_value": 0.003122994336538018,
      "significant": true,
      "interpretation": "UNKNOWN - dimension eludes interpretation",
      "note": "Correlation exists. Mechanism remains mysterious.",
      "p_value_bonferroni": 0.053090903721146304,
      "p_value_fdr": 0.00894856371210251,
      "significant_bonferroni": false,
      "significant_fdr": true
    },
    {
      "pattern_id": "latent_dim_5",
      "correlation_type": "latent_dimension",
      "effect_size": 0.12932788585220487,
      "p_value": 0.00454012092742847,
      "significant": true,
      "interpretation": "UNKNOWN - dimension eludes interpretation",
      "note": "Correlation exists. Mechanism remains mysterious.",
      "p_value_bonferroni": 0.077182055766284,
      "p_value_fdr": 0.00894856371210251,
      "significant_bonferroni": false,
      "significant_fdr": true
    },
    {
      "pattern_id": "latent_dim_15",
      "correlation_type": "latent_dimension",
      "effect_size": 0.12655643314201234,
      "p_value": 0.005492132459747504,
      "significant": true,
      "interpretation": "UNKNOWN - dimension eludes interpretation",
      "note": "Correlation exists. Mechanism remains mysterious.",
      "p_value_bonferroni": 0.09336625181570757,
      "p_value_fdr": 0.01211640525648907,
      "significant_bonferroni": false,
      "significant_fdr": true
    },
    {
      "pattern_id": "latent_dim_19",
      "correlation_type": "latent_dimension",
      "effect_size": 0.1173250690305293,
      "p_value": 0.010092259004206053,
      "significant": true,
      "interpretation": "UNKNOWN - dimension eludes interpretation",
      "note": "Correlation exists. Mechanism remains mysterious.",
      "p_value_bonferroni": 0.1715684030715029,
      "p_value_fdr": 0.02859473384525048,
      "significant_bonferroni": false,
      "significant_fdr": true
    },
    {
      "pattern_id": "latent_dim_3",
      "correlation_type": "latent_dimension",
      "effect_size": -0.1099493871068654,
      "p_value": 0.015956888583754807,
      "significant": true,
      "interpretation": "UNKNOWN - dimension eludes interpretation",
      "note": "Correlation exists. Mechanism remains mysterious.",
      "p_value_bonferroni": 0.27126710592383174,
      "p_value_fdr": 0.00894856371210251,
      "significant_bonferroni": false,
      "significant_fdr": true
    },
    {
      "pattern_id": "latent_dim_2",
      "correlation_type": "latent_dimension",
      "effect_size": 0.10163553796720819,
      "p_value": 0.025968261702433902,
      "significant": true,
      "interpretation": "UNKNOWN - dimension eludes interpretation",
      "note": "Correlation exists. Mechanism remains mysterious.",
      "p_value_bonferroni": 0.4414604489413763,
      "p_value_fdr": 0.00894856371210251,
      "significant_bonferroni": false,
      "significant_fdr": true
    },
    {
      "pattern_id": "latent_dim_10",
      "correlation_type": "latent_dimension",
      "effect_size": 0.09993497902126654,
      "p_value": 0.028579396234235117,
      "significant": true,
      "interpretation": "UNKNOWN - dimension eludes interpretation",
      "note": "Correlation exists. Mechanism remains mysterious.",
      "p_value_bonferroni": 0.485849735981997,
      "p_value_fdr": 0.01211640525648907,
      "significant_bonferroni": false,
      "significant_fdr": true
    }
  ],
  "all_correlations": [
    {
      "pattern_id": "pattern_2",
      "correlation_type": "cluster_membership",
      "effect_size": 0.3355545925289881,
      "p_value": 0.010779944887902536,
      "significant": true,
      "cluster_mean": 0.19253731343283584,
      "other_mean": 0.137046004842615,
      "test": "t-test",
      "n_in_cluster": 67,
      "p_value_bonferroni": 0.18325906309434312,
      "p_value_fdr": 0.00894856371210251,
      "significant_bonferroni": false,
      "significant_fdr": true
    },
    {
      "pattern_id": "pattern_4",
      "correlation_type": "cluster_membership",
      "effect_size": -0.26527013262070653,
      "p_value": 0.10095544610309053,
      "significant": false,
      "cluster_mean": 0.10476190476190475,
      "other_mean": 0.14863013698630137,
      "test": "t-test",
      "n_in_cluster": 42,
      "p_value_bonferroni": 1.0,
      "p_value_fdr": 0.00894856371210251,
      "significant_bonferroni": false,
      "significant_fdr": true
    },
    {
      "pattern_id": "pattern_3",
      "correlation_type": "cluster_membership",
      "effect_size": -0.1863793868599015,
      "p_value": 0.24947999954230257,
      "significant": false,
      "cluster_mean": 0.11666666666666667,
      "other_mean": 0.14748858447488583,
      "test": "t-test",
      "n_in_cluster": 42,
      "p_value_bonferroni": 1.0,
      "p_value_fdr": 0.00894856371210251,
      "significant_bonferroni": false,
      "significant_fdr": true
    },
    {
      "pattern_id": "pattern_7",
      "correlation_type": "cluster_membership",
      "effect_size": 0.16693651926734054,
      "p_value": 0.33032806398945425,
      "significant": false,
      "cluster_mean": 0.17027027027027028,
      "other_mean": 0.14266365688487584,
      "test": "t-test",
      "n_in_cluster": 37,
      "p_value_bonferroni": 1.0,
      "p_value_fdr": 0.00894856371210251,
      "significant_bonferroni": false,
      "significant_fdr": true
    },
    {
      "pattern_id": "latent_dim_17",
      "correlation_type": "latent_dimension",
      "effect_size": 0.15396605673860064,
      "p_value": 0.0007127297209699453,
      "significant": true,
      "interpretation": "UNKNOWN - dimension eludes interpretation",
      "note": "Correlation exists. Mechanism remains mysterious.",
      "p_value_bonferroni": 0.01211640525648907,
      "p_value_fdr": 0.01211640525648907,
      "significant_bonferroni": true,
      "significant_fdr": true
    },
    {
      "pattern_id": "latent_dim_6",
      "correlation_type": "latent_dimension",
      "effect_size": 0.14908191058699277,
      "p_value": 0.0010527722014238247,
      "significant": true,
      "interpretation": "UNKNOWN - dimension eludes interpretation",
      "note": "Correlation exists. Mechanism remains mysterious.",
      "p_value_bonferroni": 0.01789712742420502,
      "p_value_fdr": 0.00894856371210251,
      "significant_bonferroni": true,
      "significant_fdr": true
    },
    {
      "pattern_id": "latent_dim_0",
      "correlation_type": "latent_dimension",
      "effect_size": 0.13462974326132812,
      "p_value": 0.003122994336538018,
      "significant": true,
      "interpretation": "UNKNOWN - dimension eludes interpretation",
      "note": "Correlation exists. Mechanism remains mysterious.",
      "p_value_bonferroni": 0.053090903721146304,
      "p_value_fdr": 0.00894856371210251,
      "significant_bonferroni": false,
      "significant_fdr": true
    },
    {
      "pattern_id": "pattern_6",
      "correlation_type": "cluster_membership",
      "effect_size": -0.13035463754520674,
      "p_value": 0.32948855935291177,
      "significant": false,
      "cluster_mean": 0.12615384615384614,
      "other_mean": 0.14771084337349397,
      "test": "t-test",
      "n_in_cluster": 65,
      "p_value_bonferroni": 1.0,
      "p_value_fdr": 0.00894856371210251,
      "significant_bonferroni": false,
      "significant_fdr": true
    },
    {
      "pattern_id": "latent_dim_5",
      "correlation_type": "latent_dimension",
      "effect_size": 0.12932788585220487,
      "p_value": 0.00454012092742847,
      "significant": true,
      "interpretation": "UNKNOWN - dimension eludes interpretation",
      "note": "Correlation exists. Mechanism remains mysterious.",
      "p_value_bonferroni": 0.077182055766284,
      "p_value_fdr": 0.00894856371210251,
      "significant_bonferroni": false,
      "significant_fdr": true
    },
    {
      "pattern_id": "latent_dim_15",
      "correlation_type": "latent_dimension",
      "effect_size": 0.12655643314201234,
      "p_value": 0.005492132459747504,
      "significant": true,
      "interpretation": "UNKNOWN - dimension eludes interpretation",
      "note": "Correlation exists. Mechanism remains mysterious.",
      "p_value_bonferroni": 0.09336625181570757,
      "p_value_fdr": 0.01211640525648907,
      "significant_bonferroni": false,
      "significant_fdr": true
    },
    {
      "pattern_id": "latent_dim_19",
      "correlation_type": "latent_dimension",
      "effect_size": 0.1173250690305293,
      "p_value": 0.010092259004206053,
      "significant": true,
      "interpretation": "UNKNOWN - dimension eludes interpretation",
      "note": "Correlation exists. Mechanism remains mysterious.",
      "p_value_bonferroni": 0.1715684030715029,
      "p_value_fdr": 0.02859473384525048,
      "significant_bonferroni": false,
      "significant_fdr": true
    },
    {
      "pattern_id": "latent_dim_3",
      "correlation_type": "latent_dimension",
      "effect_size": -0.1099493871068654,
      "p_value": 0.015956888583754807,
      "significant": true,
      "interpretation": "UNKNOWN - dimension eludes interpretation",
      "note": "Correlation exists. Mechanism remains mysterious.",
      "p_value_bonferroni": 0.27126710592383174,
      "p_value_fdr": 0.00894856371210251,
      "significant_bonferroni": false,
      "significant_fdr": true
    },
    {
      "pattern_id": "latent_dim_2",
      "correlation_type": "latent_dimension",
      "effect_size": 0.10163553796720819,
      "p_value": 0.025968261702433902,
      "significant": true,
      "interpretation": "UNKNOWN - dimension eludes interpretation",
      "note": "Correlation exists. Mechanism remains mysterious.",
      "p_value_bonferroni": 0.4414604489413763,
      "p_value_fdr": 0.00894856371210251,
      "significant_bonferroni": false,
      "significant_fdr": true
    },
    {
      "pattern_id": "latent_dim_10",
      "correlation_type": "latent_dimension",
      "effect_size": 0.09993497902126654,
      "p_value": 0.028579396234235117,
      "significant": true,
      "interpretation": "UNKNOWN - dimension eludes interpretation",
      "note": "Correlation exists. Mechanism remains mysterious.",
      "p_value_bonferroni": 0.485849735981997,
      "p_value_fdr": 0.01211640525648907,
      "significant_bonferroni": false,
      "significant_fdr": true
    },
    {
      "pattern_id": "pattern_0",
      "correlation_type": "cluster_membership",
      "effect_size": 0.035993902753367446,
      "p_value": 0.7947636238662645,
      "significant": false,
      "cluster_mean": 0.15000000000000002,
      "other_mean": 0.14404761904761904,
      "test": "t-test",
      "n_in_cluster": 60,
      "p_value_bonferroni": 1.0,
      "p_value_fdr": 0.00894856371210251,
      "significant_bonferroni": false,
      "significant_fdr": true
    },
    {
      "pattern_id": "pattern_1",
      "correlation_type": "cluster_membership",
      "effect_size": -0.02427433946735715,
      "p_value": 0.820880768532456,
      "significant": false,
      "cluster_mean": 0.14173913043478262,
      "other_mean": 0.14575342465753424,
      "test": "t-test",
      "n_in_cluster": 115,
      "p_value_bonferroni": 1.0,
      "p_value_fdr": 0.00894856371210251,
      "significant_bonferroni": false,
      "significant_fdr": true
    },
    {
      "pattern_id": "pattern_5",
      "correlation_type": "cluster_membership",
      "effect_size": -0.0038038128718511813,
      "p_value": 0.9793898962448261,
      "significant": false,
      "cluster_mean": 0.14423076923076922,
      "other_mean": 0.14485981308411214,
      "test": "t-test",
      "n_in_cluster": 52,
      "p_value_bonferroni": 1.0,
      "p_value_fdr": 0.00894856371210251,
      "significant_bonferroni": false,
      "significant_fdr": true
    }
  ],
  "validation": {
    "safe_to_proceed": true,
    "issues": [],
    "warnings": [
      "High significance rate (100%) with strong effects (median 0.15)",
      "Pattern count differs from \u03c0 prediction (exp 21, got 8)"
    ]
  }
}